license.md
readme.md
requirements.txt
setup.py
.github/workflows/build_tests.yml
.github/workflows/license_tests.yml
examples/convenience.py
examples/disambiuation.py
examples/parsing.py
examples/quick_questions.py
examples/voice_assistants.py
test/license_tests.py
test/test_human_funcs.py
test/test_utils.py
wikipedia_for_humans/__init__.py
wikipedia_for_humans/exceptions.py
wikipedia_for_humans/util.py
wikipedia_for_humans.egg-info/PKG-INFO
wikipedia_for_humans.egg-info/SOURCES.txt
wikipedia_for_humans.egg-info/dependency_links.txt
wikipedia_for_humans.egg-info/requires.txt
wikipedia_for_humans.egg-info/top_level.txt