Metadata-Version: 2.1
Name: wikipedia-for-humans
Version: 0.3.2
Summary: wikipedia for humans
Home-page: https://github.com/OpenJarbas/wikipedia_for_humans
Author: jarbasAI
Author-email: jarbasai@mailfence.com
License: MIT
